examples/__init__.py
examples/bot.py
examples/bot_gym.py
examples/example_manual.py
gym_lartpc/__init__.py
gym_lartpc/envs/__init__.py
gym_lartpc/envs/lartpc.py
lartpc_game/__init__.py
lartpc_game/data.py
lartpc_game/version.py
lartpc_game/viz.py
lartpc_game/agents/__init__.py
lartpc_game/agents/agents.py
lartpc_game/agents/observables.py
lartpc_game/agents/settings.py
lartpc_game/agents/tools.py
lartpc_game/game/__init__.py
lartpc_game/game/cursors.py
lartpc_game/game/dims.py
lartpc_game/game/game_ai.py
lartpc_game/game/regions.py
gym_lartpc-0.0.10.dist-info/METADATA
gym_lartpc-0.0.10.dist-info/WHEEL
gym_lartpc-0.0.10.dist-info/top_level.txt
gym_lartpc-0.0.10.dist-info/RECORD
