Metadata-Version: 2.1
Name: gym-lartpc
Version: 0.0.10
Summary: Openai-gym compatible reinforcement learning env for lartpc data
Home-page: https://githum.com/mmajewsk/gym-lartpc2d
Author: Maciej Majewski
Author-email: mmajewsk@cern.ch
License: UNKNOWN
Platform: UNKNOWN
Requires-Dist: pandas (>=1.0.0)
Requires-Dist: scipy (>=1.4.1)
Requires-Dist: opencv-python (>=4.2.0.32)
Requires-Dist: numpy (>=1.18.1)
Requires-Dist: matplotlib (>=3.1.3)
Requires-Dist: nptyping (>=1.3.0)
Requires-Dist: gym
